auth/__init__.py
auth/auth_client.py
auth/log_client.py
config/AppConfig.py
config/__init__.py
utils/__init__.py
utils/sign_utils.py
pgver_api_auth-0.1.0.dist-info/METADATA
pgver_api_auth-0.1.0.dist-info/WHEEL
pgver_api_auth-0.1.0.dist-info/top_level.txt
pgver_api_auth-0.1.0.dist-info/RECORD
