Metadata-Version: 2.4
Name: pgver_api_auth
Version: 0.1.0
Summary: A short description of your package
Home-page: http://gitlab.os.hi.cn:60080/pgv_base/api-platform-auth-sdk#
Author: Your Name
Author-email: jingzhi.lu@pgverse.ai
Classifier: Programming Language :: Python :: 3
Classifier: License :: OSI Approved :: MIT License
Classifier: Operating System :: OS Independent
Requires-Dist: requests>=2.24.0
Dynamic: author
Dynamic: author-email
Dynamic: classifier
Dynamic: description
Dynamic: description-content-type
Dynamic: home-page
Dynamic: requires-dist
Dynamic: summary
